scramjet/__init__.py
scramjet/ansi_color_codes.py
scramjet/pyfca.py
scramjet/streams.py
scramjet/utils.py
scramjet_framework_py-0.10.1.dist-info/LICENSE
scramjet_framework_py-0.10.1.dist-info/METADATA
scramjet_framework_py-0.10.1.dist-info/WHEEL
scramjet_framework_py-0.10.1.dist-info/top_level.txt
scramjet_framework_py-0.10.1.dist-info/RECORD
