Metadata-Version: 2.1
Name: scramjet-framework-py
Version: 0.10.1
Summary: Scramjet is a simple reactive stream programming framework.
Author: Scramjet.org
Author-email: <info@scramjet.org>
Keywords: python,streams
License-File: LICENSE
